pykatex.cpython-313-darwin.so
quickjs/libregexp.c
quickjs/quickjs.c
quickjs/libunicode-table.h
quickjs/quickjs-c-atomics.h
quickjs/libunicode.c
quickjs/xsum.h
quickjs/dirent_compat.h
quickjs/cutils.c
quickjs/quickjs-libc.c
quickjs/builtin-array-fromasync.h
quickjs/libregexp-opcode.h
quickjs/list.h
quickjs/quickjs-opcode.h
quickjs/libregexp.h
quickjs/quickjs-atom.h
quickjs/quickjs.h
quickjs/unicode_gen_def.h
quickjs/libunicode.h
quickjs/quickjs-libc.h
quickjs/xsum.c
quickjs/cutils.h
pykatex-0.1.0.dist-info/RECORD
pykatex-0.1.0.dist-info/WHEEL
pykatex-0.1.0.dist-info/top_level.txt
pykatex-0.1.0.dist-info/METADATA
pykatex-0.1.0.dist-info/licenses/LICENSE
