Metadata-Version: 2.4
Name: PyKaTeX
Version: 0.1.0
Summary: A Python wrapper for the KaTeX library, providing fast server-side rendering of mathematical expressions.
Author-email: Ruben van Nieuwpoort <ruben@vannieuwpoort.dev>
License-Expression: MIT
Project-URL: homepage, https://github.com/rubenvannieuwpoort/PyKaTeX
Classifier: Development Status :: 3 - Alpha
Classifier: Programming Language :: Python :: 3
Requires-Python: >=3
License-File: LICENSE
Dynamic: license-file
